dissect/util/__init__.py
dissect/util/_build.py
dissect/util/cpio.py
dissect/util/exceptions.py
dissect/util/feature.py
dissect/util/plist.py
dissect/util/sid.py
dissect/util/stream.py
dissect/util/ts.py
dissect/util/xmemoryview.py
dissect/util/_native/__init__.pyi
dissect/util/_native/compression/__init__.pyi
dissect/util/_native/compression/lz4.pyi
dissect/util/_native/compression/lzo.pyi
dissect/util/compression/__init__.py
dissect/util/compression/lz4.py
dissect/util/compression/lznt1.py
dissect/util/compression/lzo.py
dissect/util/compression/lzxpress.py
dissect/util/compression/lzxpress_huffman.py
dissect/util/compression/sevenbit.py
dissect/util/compression/xz.py
dissect/util/encoding/__init__.py
dissect/util/encoding/surrogateescape.py
dissect/util/hash/__init__.py
dissect/util/hash/crc32c.py
dissect/util/hash/jenkins.py
dissect/util/tools/__init__.py
dissect/util/tools/dump_nskeyedarchiver.py
dissect_util-3.22.dist-info/licenses/COPYRIGHT
dissect_util-3.22.dist-info/licenses/LICENSE
dissect_util-3.22.dist-info/METADATA
dissect_util-3.22.dist-info/WHEEL
dissect_util-3.22.dist-info/entry_points.txt
dissect_util-3.22.dist-info/top_level.txt
dissect_util-3.22.dist-info/RECORD
