Metadata-Version: 2.4
Name: dissect.util
Version: 3.22
Summary: A Dissect module implementing various utility functions for the other Dissect modules
Author-email: Dissect Team <dissect@fox-it.com>
License-Expression: Apache-2.0
Project-URL: homepage, https://dissect.tools
Project-URL: documentation, https://docs.dissect.tools/en/latest/projects/dissect.util
Project-URL: repository, https://github.com/fox-it/dissect.util
Classifier: Development Status :: 5 - Production/Stable
Classifier: Environment :: Console
Classifier: Intended Audience :: Developers
Classifier: Intended Audience :: Information Technology
Classifier: Operating System :: OS Independent
Classifier: Programming Language :: Python :: 3
Classifier: Topic :: Internet :: Log Analysis
Classifier: Topic :: Scientific/Engineering :: Information Analysis
Classifier: Topic :: Security
Classifier: Topic :: Utilities
Requires-Python: ~=3.9
License-File: LICENSE
License-File: COPYRIGHT
Dynamic: license-file
